ofxstatement_lloyds/__init__.py
ofxstatement_lloyds/plugin.py
ofxstatement_lloyds-1.0.0.dist-info/METADATA
ofxstatement_lloyds-1.0.0.dist-info/WHEEL
ofxstatement_lloyds-1.0.0.dist-info/entry_points.txt
ofxstatement_lloyds-1.0.0.dist-info/top_level.txt
ofxstatement_lloyds-1.0.0.dist-info/RECORD
