Metadata-Version: 2.1
Name: ofxstatement-lloyds
Version: 1.0.0
Summary: Plugin for reading statements of Lloyds UK bank
Author-email: Victoria Lebedeva <victoria@lebedev.lt>
Project-URL: Homepage, https://github.com/Metasaura/ofxstatement-lloyds
Keywords: ofx,banking,statement,lloyds
Classifier: Development Status :: 5 - Production/Stable
Classifier: Programming Language :: Python :: 3
Classifier: Natural Language :: English
Classifier: Topic :: Office/Business :: Financial :: Accounting
Classifier: Topic :: Utilities
Classifier: Environment :: Console
Classifier: Operating System :: OS Independent
Classifier: License :: OSI Approved :: MIT License
Requires-Python: >=3.9
Requires-Dist: ofxstatement
